{"meta":{"domain":"places","kid":"23672","authors":[{"id":"52","fullname":"Yudru Tsomu"},{"id":"52","fullname":"Yudru Tsomu"}],"title":"An Overview of Muli","dates":{"created_at":"2011-07-13 16:54:01 UTC","updated_at":"2011-07-13 16:54:01 UTC"}},"nodes":[{"index":0,"parent_index":-1,"body":"<p>Sent by the third Dalai Lama in the 1580s to propagate Buddhism, Chökyi Sanggyé Gyatso (<em><span class=\"tibetan\" title=\"Type ID here\">chos kyi sangs rgyas rgya mtsho</span></em>) named himself the first dharma king of Muli (<em><span class=\"tibetan\" title=\"Type ID here\">mu li</span></em>). The kingdom’s religious affairs were under the direct leadership of the Dalai Lamas and the Three Great Monastic Seats (<em><span class=\"tibetan\" title=\"Type ID here\">gdan sa gsum</span></em>) in Lhasa, whereas its political affairs were largely under the control of the Qing. In 1729 the Qing government granted the title of Pacification Commissioner (<em><span class=\"chinese\" title=\"Type ID here\">anfusi</span></em>, 安抚司) to the sixth king Lopsang Tupten (<em><span class=\"tibetan\" title=\"Type ID here\">blo bzang thub bstan</span></em>), and in 1868 it granted the title of <em><span class=\"chinese\" title=\"Type ID here\">xuanweisi</span></em> on the thirteenth king Sönam Trashi (<em><span class=\"tibetan\" title=\"Type ID here\">bsod nams bkra shis</span></em>).</p>","title":"An Overview of Muli"}]}