{"meta":{"authors":[{"id":"80","fullname":"ཚེ་རིང་ཐར། (Tsering Thar)"},{"id":"80","fullname":"ཚེ་རིང་ཐར། (Tsering Thar)"}],"title":"Nangzhik Gyelten Püntsok Ling Introduction","dates":{"created_at":"2011-12-13 02:30:15 UTC","updated_at":"2011-12-13 02:30:15 UTC"}},"nodes":[{"index":0,"parent_index":-1,"title":"Nangzhik Gyelten Püntsok Ling Introduction"},{"title":"rNga khog","index":1,"parent_index":0,"body":"\n\n                  "},{"title":"(180) sNang zhig Monastery","index":2,"parent_index":1,"body":"\n\n                  \n\n                     "},{"title":"1. Name","index":3,"parent_index":2,"body":"\n\n                     <p>The monastery&rsquo;s full name is sNang zhig rGyal bstan phun tshogs gling, and\n                        is also known as sNang zhig bKra shis g-yung drung gling, or sNang zhig\n                        Phyogs las rnam rgyal bkra shis g-yung drung gling.</p>\n\n                  \n\n                  \n\n                     "},{"title":"2. Location","index":4,"parent_index":2,"body":"\n\n                     <p>The monastery is located 5 km north of rNga ba Township, the seat of rNga ba\n                        county. There is a motorable road leading to the monastery.</p>\n\n                  \n\n                  \n\n                     "},{"title":"3. History","index":5,"parent_index":2,"body":"\n\n                     <p>The first in the succession of the sNang zhig masters is said to be Do\n                        &rsquo;phags chen po, also known as Yon tan rgyal mtshan (b.1168).<a href=\"#n55\" name=\"nb55\" class=\"note\">55</a> Although the latter was responsible for spreading Bon in the area\n                        and opened several hermitages in rNga khog, the real founder of the\n                        monastery was Nyi ma &rsquo;dzin, the eldest son of Do &rsquo;phags chen po. The first\n                        building of the establishment was Nyi ma &rsquo;dzin&rsquo;s own residence (bla brang)\n                        built in 1108 and known as rGyal bstan phun tshogs gling. </p>\n\n                     <p>Do &rsquo;phags chen po and sKyang za g-yu sgron had three sons: Nyi ma &rsquo;dzin,\n                        &rsquo;Dul ba rgyal mtshan, and gYung drung rgyal mtshan. Nyi ma &rsquo;dzin studied\n                        under the feet of Zhu sgom &rsquo;phrul zhig, but his two brothers &rsquo;Dul ba rgyal\n                        mtshan and gYung drung rgyal mtshan migrated to Shar khog where the former\n                        founded the monastery lCags mdud bKra shis g-yung drung gling (No.199), and\n                        the latter a monastery known as sNang zhig dngul sku (No.201). </p>\n\n                     <p>The descendants of the three brothers were collectively known as the &ldquo;three\n                        lineages of sNang zhig&rdquo; (sNang zhig khag gsum). The twenty-fourth descendant\n                        of the eldest brother, sNang zhig Tshul khrims dbang mchog, took monastic\n                        vows. He then divided the establishment of sNang zhig rGyal bstan phun\n                        tshogs gling into two settlements: one for lay tantric practitioners and the\n                        other for monks. </p>\n\n                     <p>Following is a list of the sNang zhig lineage masters: </p>\n\n                     <ol type=\"1\">\n                        <li>Do &rsquo;phags chen po (sNang zhig Yon tan rgyal mtshan </li>\n\n                        <li>Nyi ma &rsquo;dzin </li>\n\n                        <li>lHun grub rgyal mtshan </li>\n\n                        <li>Kun dga&rsquo; rgyal mtshan </li>\n\n                        <li>Nam mkha&rsquo; rgyal mtshan </li>\n\n                        <li>Zla ba rgyal mtshan </li>\n\n                        <li>Yon tan rgyal mtshan </li>\n\n                        <li>Kun dga&rsquo; lhun grub </li>\n\n                        <li>Shes rab rgyal mtshan </li>\n\n                        <li>lHun grub rgyal mtshan </li>\n\n                        <li>Shes rab &rsquo;od zer </li>\n\n                        <li>Chags med bya bral </li>\n\n                        <li>bstan pa rgyal mtshan </li>\n\n                        <li>Tshul khrims rgyal mtshan </li>\n\n                        <li>Ye shes rgyal mtshan </li>\n\n                        <li>bSod nams rgyal mtshan </li>\n\n                        <li>lHun grub dbang ldan </li>\n\n                        <li>bsTan pa tshul khrims </li>\n\n                        <li>Rin chen lhun grub </li>\n\n                        <li>Shes rab rgyal ba </li>\n\n                        <li>Nam mkha&rsquo; rgyal mtshan </li>\n\n                        <li>Shes rab dbang rgyal </li>\n\n                        <li>Tshe dbang rgyal mtshan </li>\n\n                        <li>Tshul khrims dbang mchog </li>\n\n                        <li>bsTan pa tshul khrims </li>\n\n                        <li>bsTan pa lhun grub </li>\n\n                        <li>Shes rab blo gros </li>\n\n                        <li>Tshul khrims bstan &rsquo;dzin </li>\n\n                        <li>Rin chen rgyal mtshan, </li>\n\n                        <li>gYung drung bstan pa dar rgyas, he founded gDong li Monastery\n                           (No.179)</li>\n\n                        <li>bSod nams rgyal mtshan </li>\n\n                        <li>bsTan &rsquo;dzin dbang rgyal </li>\n\n                        <li>Phun tshogs rnam rgyal </li>\n\n                        <li>Blo gros thogs med </li>\n\n                        <li>gYung drung bstan pa&rsquo;i nyi ma </li>\n\n                        <li>Grub dbang g-yung drung bstan &rsquo;dzin </li>\n\n                        <li>Nam mkha&rsquo; blo gros </li>\n\n                        <li>bsTan pa rab rgyas (1929-1961)</li>\n\n                        <li>bsKal bzang blo gros rgya mtsho (b.1983)</li>\n                     </ol>\n\n                     <p>The monastery was destroyed during the Cultural Revolution and its\n                        reconstruction was undertaken in 1980 by rGya &rsquo;obs bsTan &rsquo;dzin dbang rgyal\n                        and Slob zur Tshul khrims bstan &rsquo;dzin.</p>\n\n                  \n\n                  \n\n                     "},{"title":"4. Hierarchical system","index":6,"parent_index":2,"body":"\n\n                     <p>The sNang zhig family is the &ldquo;owner of the monastery&rdquo; (dgon bdag) and the\n                        present head of the monastery is sNang zhig bsKal bzang blo gros rgya mtsho\n                        (b.1983). The monastery is therefore headed by an hereditary line.</p>\n\n                     <ul xmlns:str=\"http://exslt.org/strings\" class=\"bullet-blue\">\n                        <li>rgyal tshab</li>\n\n                        <li>one khri pa, replaced every year</li>\n\n                        <li>one dpon sbob, replaced every three year</li>\n\n                        <li>two dpe khrid, (teachers), replaced every two years</li>\n\n                        <li>three dge skos, replaced every year </li>\n\n                        <li>two dbu mdzad, replaced every six years (after three years the younger\n                           dbu mdzad (dbu mdzad chung ba) replaces the dbu mdzad che ba, the elder\n                           dbu mdzad) </li>\n\n                        <li>two mchod g-yog, replaced every two years (after one year the mchod\n                           g-yog chung ba, the younger mchod g-yog, replaces the mchod g-yog che ba,\n                           the elder mchod g-yog) </li>\n\n                        <li>seven lha gnyer, replaced each year; one gnyer chen, replaced each\n                           year </li>\n\n                        <li>two yig mkhan (accountant) replaced every two years </li>\n\n                        <li>two drung yig, replaced every three years </li>\n                     </ul>\n\n                  \n\n                  \n\n                     "},{"title":"5. Current number of monks","index":7,"parent_index":2,"body":"\n\n                     <p>There are seven hundred novices and monks in the monastery.</p>\n\n                  \n\n                  \n\n                     "},{"title":"6. Current education","index":8,"parent_index":2,"body":"\n\n                     <p>There are thirteen classes devoted to the following metaphysic subjects: 1)\n                        Kha tog dkar dmar, 2) bsDus chung, 3) bsDus &rsquo;bring, 4) bsDus chen, 5) Blo\n                        rig, 6) rTags rig, 7) gZhung gsar, 8) gZhung gong sa lam, 9) Phar phyin, 10)\n                        &rsquo;Dul mdzod (grade: rdo rams &rsquo;og ma), 11) dBu ma (grade: rdo rams gong ma),\n                        12) sNgags, 13) rDzogs chen. </p>\n\n                     <p>For the above subjects the students use the bsDus grwa by mKhan chen Nyi ma\n                        bstan &rsquo;dzin; the works on the Khams chen by dPal chen; the five &rsquo;Phrul sgron\n                        by mNyam med Shes rab rgyal mtshan and commentaries on the Gab pa, mDzod and\n                        Sa lam written by scholars from gYas ru dBen sa kha Monastery.</p>\n\n                     <p>The monk students have classes and debate every day except during retreats;\n                        the texts they study during retreats include texts that deal with meditation\n                        systems of A khrid, sNyan brgyud and rDzogs chen.</p>\n\n                     <p>Monks of the college of ritual practice (sgrub gwra) must complete the three\n                        year retreat (lo gsum) following the A khrid tradition of meditation.</p>\n\n                  \n\n                  \n\n                     "},{"title":"7. Educational exchange","index":9,"parent_index":2,"body":"\n\n                     <p>sNang zhig is the largest monastic university of Bon religion in Tibet. Many\n                        monks from various monasteries throughout Amdo and Khams visit the\n                        monastery. sNang zhig Monastery sends its monks to teach at Tsha lung\n                        Monastery (No.193) in rMe ba, &rsquo;Bol la (No.182) and Kun &rsquo;brog (No.183)\n                        monasteries of &rsquo;Bar khams in rGyal rong, lCags mdud (No.199) and sNang zhig\n                        dNgul sku (No.201) in Shar khog, rTse dbus Monastery (No.99) in rGan rgya,\n                        Dung dkar Monastery (No.132) in Chab cha, Khyung mo Monastery (No.123) in\n                        Khri ka and Bon brgya Monastery (No.100) in Reb gong.</p>\n\n                  \n\n                  \n\n                     "},{"title":"8 / 9. Rituals","index":10,"parent_index":2,"body":"\n\n                     <ul xmlns:str=\"http://exslt.org/strings\" class=\"bullet-blue\">\n                        <li>1st month: commemoration of sNyam med Shes rab rgyal mtshan from the\n                           4th to the 6th day</li>\n\n                        <li>2nd month: commemoration of Nang chen Kun bzang bstan pa&rsquo;i rgyal\n                           mtshan from the 1st to the 5th day and that of rGya &rsquo;obs bsTan pa rab\n                           rgyas from the 7th to the 13th day </li>\n\n                        <li>3rd month: the ritual based on the Yi dam kun &rsquo;dus from the 8th day\n                           for three days and the ritual cycle of Ma rgyud from the 11th for four\n                           days </li>\n\n                        <li>4th month: the recitation of the mantra Ma tri on the 14th day</li>\n\n                        <li>5th month: the ceremony of the lighting of 10,000 butter lamps as\n                           offering to rNam rgyal, an aspect of gShen rab Mi bo, for ten days from\n                           the 6th day</li>\n\n                        <li>6th month: the ritual cycle of Phur pa from the 3rd day for seven\n                           days; the observance of summer-fast (dbyar gnas) for seven days from the\n                           15th day; the ceremony of Dus khrims for seven days from the 24th\n                           day</li>\n\n                        <li>11th month: commemoration of sKyabs mgon Zla ba rgyal mtshan on the\n                           7th and 8th days </li>\n\n                        <li>12th month: the ritual of the gShen rab sgrub mchod for three days\n                           from the 14th day and the dgu gtor rite for four days from the 26th\n                           day</li>\n                     </ul>\n\n                  \n\n                  \n\n                     "},{"title":"10. Books held in the monastery","index":11,"parent_index":2,"body":"\n\n                     <p>Printed editions: five copies of the Bonpo Kanjur and six copies of the\n                        Bonpo Katen, and more than 2000 printing blocks.</p>\n\n                  \n\n                  \n\n                     "},{"title":"11. Income and expenses","index":12,"parent_index":2,"body":"\n\n                     <p>The monastery depends on offerings from the faithful and also owns a hotel\n                        in the county town.</p>\n\n                  \n\n                  \n\n                     "},{"title":"12. Local community","index":13,"parent_index":2,"body":"\n\n                     <p>The local community consists of twenty-eight villages: mChog skyid with\n                        thirteen families, &rsquo;Ju skor with thirty families, A ka with sixty-four\n                        families, Cha bo with forty-one families, Ber rtsa with thirty-seven\n                        families, Thar ba with sixty families, Ho tsa with fifteen families, Hor\n                        &rsquo;phen with thirteen families, Khos &rsquo;go with seventeen families, Kha shu with\n                        twenty-seven families, Bon sde with seventy-five families, sPrel mgo with\n                        fifteen families, gTsang ra with ten families, Zhag &rsquo;dug with five families,\n                        Zhes &rsquo;phen with twenty-eight families, Grong mang with ten families, Thes\n                        grong with twenty families, Khos mgo rtsa with eighteen families, mGon shul\n                        with thirteen families, sTag rtsa with eighteen families, &rsquo;Tshams ring lcag\n                        with twenty-eight families, mTha&rsquo; ba with fifteen families, mGo che lcag\n                        with thirty-eight families, Ka shul &rsquo;gab ma with forty-five families, Ka\n                        shul gong ma with twenty-five families, Chu kha ra with five families, dGe\n                        lu with seventeen families, Mag gsar with fifteen families. (717 families\n                        altogether)</p>\n\n                  \n\n                  \n\n                     "},{"title":"13. Local festivals","index":14,"parent_index":2,"body":"\n\n                     <p>The mountain behind the monastery, rBang brtsan bse khrab can, is located\n                        about 10 km north of the monastery. There is a la btsas at the top whose\n                        renewal celebration, which is attended by both religious and lay\n                        communities, takes place on the 11th day of the 4th month. In addition, the\n                        members of the sNang zhig family traditionally propitiated the local deity\n                        (yul lha) of Mount gNyan po g-yu rtse, located in southeast of Golok, 5368\n                        meters high, but the custom was interrupted in the 1960s. Recently it was\n                        revived by the present head of the sNang zhig family. There is also a\n                        &ldquo;sacred mountain&rdquo; (gnas ri) called dGon lung, situated about 4 km northwest\n                        of the monastery. It was sanctified by sNang zhig Nam mkha&rsquo; blo gros. Its\n                        veneration by the local people takes place every Horse Year. </p>\n\n                  \n\n                  \n\n                     "},{"title":"14. Occupation of the local people","index":15,"parent_index":2,"body":"\n\n                     <p>Farmers and traders</p>\n\n                  \n\n                  \n\n                     "},{"title":"Sources","index":16,"parent_index":2,"body":"\n\n                     \n\n                        "},{"title":"(1) Interviews","index":17,"parent_index":16,"body":"\n\n                        <p>In autumn 1998 with: rGya &rsquo;obs bsTan &rsquo;dzin dbang rgyal (b.1928), the\n                           present representative (rgyal tshab) of the sNang zhig master in the\n                           monastery, and the following monks at the monastery: Nam mkha&rsquo; tshul\n                           khrims (b.1930), bsTan &rsquo;dzin ye shes (b.1931) and Phun tshogs\n                           (b.1950)</p>\n\n                     \n\n                     \n\n                        "},{"title":"(2) Texts","index":18,"parent_index":16,"body":"\n\n                        <ol type=\"1\">\n                           <li>Bon gyi &rsquo;dus sde chen po snang zhig rgyal bstan phun tshogs gling\n                              ngam bkra shis g-yung drung gling gi chags rim lo rgyus mdor bsdus\n                              shel dkar phreng ba by dGe bshes bsTan &rsquo;dzin phun tshogs and &rsquo;Jam\n                              dbyangs brtson &rsquo;grus, MS </li>\n\n                           <li>gZhi bdag gnyan po rbang btsan bse khrab can gyi bsang mchod bstod\n                              bskul (anonymous), MS</li>\n\n                           <li>gZhi bdag gnyan po g-yu rtse&rsquo;i bsang mchod bdud rtsi &rsquo;khyil ba\n                              (anonymous), MS</li>\n\n                           <li>sNang dgon dkar chag gsal ba&rsquo;i me long by Nam mkha&rsquo; tshul khrims,\n                              MS</li>\n\n                           <li>sNang zhig bkra shis g-yung drung gling gi gdan rabs rdzogs ldan\n                              ngag gi rgyal rnga by Bya &rsquo;phur Nam mkha&rsquo; rgyal mtshan, Mutri Tsedpo\n                              Zhang Bod Research Institute, Dolanji, H.P. India, 1994</li>\n\n                           <li>&ldquo;The Monastic Lineage of sNang zhig dgon pa in Amdo rNga ba&rdquo; by\n                              Donatella Rossi, The Tibet Journal, Vol. xxiii, No.4, pp.58-71, Winter\n                              1998. India</li>\n                        </ol>\n\n                     \n\n                  \n\n               <hr class=\"footnote-divider\" />"},{"title":"Notes","index":19,"parent_index":0,"body":"<div xmlns:str=\"http://exslt.org/strings\" class=\"footnote\"><a name=\"n55\" /><a href=\"#nb55\" class=\"note\">\n\t\t\t\t\t[55] </a> \n                           Per Kvaerne dated the year of his birth 1028, in &ldquo;The Monastery of\n                              sNang zhig of the Bon Religion in the rNga pa District of Amdo&rdquo;\n                              (Rivista degli Studi Orientali 63, 1990) and this is supported by the\n                              works of Nam mkha&rsquo; tshul khrims (p.9.n. MS.) and Bya &rsquo;phur Nam mkha&rsquo;\n                              rgyal mtshan (p.32) mentioned above. However, dGe bshes bsTan &rsquo;dzin\n                              phun tshogs and &rsquo;Jam dbyangs brtson &rsquo;grus give 1088, one Rab byung (60\n                              years) later in their above-mentioned works. <br />However, dGe bshes\n                              bsTan &rsquo;dzin phun tshogs and Drung ming &rsquo;Jam dbyangs brtson-&rsquo;grus give\n                              1088, one rab byung (60 years later) in their above-mentioned works.\n                              They also provide a different list of the masters from that given by\n                              Per Kvaerne (1990) whose work is based on sNang zhig do &rsquo;phags chen\n                              po&rsquo;i sku phreng gsol &rsquo;debs byin rlabs myur gzigs ma by Shes rab blo\n                              ldan (d.1999).\n                        </div>"}]}