{
 "nodes": [
  {
   "body": "<p>mdun bkyed [TBRC T1214]. Usually a preamble to empowerment. The same as Mandala ritual? Ex: Kye rdor lha dgu’i mdun sbkyed kyi cho ga (W12541). </p>", 
   "index": 0, 
   "parent_index": -1, 
   "title": "Generation [of the deity] in front [of one]"
  }
 ], 
 "meta": {
  "date": "2013-09-15 04:09:47 UTC", 
  "domain": "subjects", 
  "kid": "2451", 
  "authors": [
   {
    "fullname": "José I. Cabezón", 
    "id": "7"
   }
  ], 
  "title": "Generation [of the deity] in front [of one]"
 }
}