{
 "nodes": [
  {
   "body": "", 
   "index": 0, 
   "parent_index": -1, 
   "title": "Dhāraṇī to Free Oneself from Imprisonment"
  }, 
  {
   "body": "<ul> <li><a href=\"http://tbrc.org/#!rid=W25780\">bcings pa las grol ba'i gzungs</a></li> </ul>", 
   "index": 1, 
   "parent_index": 0, 
   "title": "Example Texts"
  }
 ], 
 "meta": {
  "authors": [
   {
    "fullname": "José I. Cabezón", 
    "id": "7"
   }
  ], 
  "domain": "subjects", 
  "kid": "1949", 
  "dates": [], 
  "title": "Dhāraṇī to Free Oneself from Imprisonment"
 }
}