{"meta":{"authors":[{"id":"6","fullname":"Nicolas Tournadre"}],"title":"","dates":{"created_at":"2013-09-15 04:15:53 UTC","updated_at":"2013-09-15 04:15:53 UTC"}},"nodes":[{"index":0,"parent_index":-1,"body":"<ul> <li>ཇ་ “Tea” (<em>jha</em>)<a href=\"#_ftn1\">[1]</a></li> <li>དོང་རྩེ་ (archaic) “Money” (*<em>dhung-tsi</em>)<a href=\"#_ftn2\">[2]</a></li> <li>ལྕོག་ཙེ་ “Table” (<em>coksi</em>, modern Chinese <em>zhuoziin</em>)</li> </ul> <hr size=\"1\" /> <p><a href=\"#_ftnref1\">[1]</a> Which is also the origin of the Arabic ∫<em>aj</em> (“shay”), Turkish <em>çaj</em> (“chay”), Russian <em>čaj</em> (“chay”), Portuguese <em>cha</em>, English tea, and French <em>thé</em>.</p> <p><a href=\"#_ftnref2\">[2]</a> The asterisk (*) here indicates a reconstructed form.</p>","title":""}]}