{
 "nodes": [
  {
   "body": "<p class=\"Paragraph\">In this case the nominalizer depends on the tense-aspect. For the present, the future, and the imperfective, the nominalizer <span class=\"tibetan\" title=\"Type ID here\">ཡག་</span> is used, whereas the perfective past uses the nominalizer <span class=\"tibetan\" title=\"Type ID here\">པ་</span>.</p><ul> <li><span class=\"tibetan\" title=\"Type ID here\">ཁྱེད་རང་གིས་བཟོས་པའི་ཁ་ལག་ཞིམ་པོ་ཞེ་དྲག་འདུག</span> “The food that you have made is very good.”</li> <li><span class=\"tibetan\" title=\"Type ID here\">ཁོང་གིས་ཞོན་ཡག་གི་རྟ་དེ་མགྱོགས་པོ་ཞེ་དྲགས་འདུག་ག</span> “The horse that he is riding is very fast.”</li> <li><span class=\"tibetan\" title=\"Type ID here\">ངས་ད་ལྟ་གློག་ཡག་གི་དེབ་དེ་སྙན་པོ་ཞེ་པོ་ཅིག་འདུག</span> “The book that I’m reading now is very interesting.”</li> </ul>", 
   "index": 0, 
   "parent_index": -1, 
   "title": "About Direct Object: “Whom,” “That,” “Which”"
  }
 ], 
 "meta": {
  "date": "2013-09-15 04:15:59 UTC", 
  "domain": "subjects", 
  "kid": "5363", 
  "authors": [
   {
    "fullname": "Nicolas Tournadre", 
    "id": "6"
   }
  ], 
  "title": "About Direct Object: “Whom,” “That,” “Which”"
 }
}