{
 "nodes": [
  {
   "body": "<p>The Pukluk (phugs lugs) astrological tradition is the normative one in Tibet currently. It is based upon work of Pukpa Lhundrub Gyatso (phugs pa lhun grub rgya mtsho), and particularly his 1447 work entitled <em>The Oral Precepts of the White Lotus</em> (pad dkar zhal lung).</p>
", 
   "index": 0, 
   "parent_index": -1, 
   "title": "An Overview of the Pukluk Calendar"
  }
 ], 
 "meta": {
  "authors": [
   {
    "fullname": "David Germano", 
    "id": "2"
   }
  ], 
  "domain": "subjects", 
  "kid": "4950", 
  "dates": [], 
  "title": "An Overview of the Pukluk Calendar"
 }
}