{
 "nodes": [
  {
   "body": "<p class=\"Paragraph\">Essential copulas express the nature or essence of the subject (equative meaning), or else an inherent quality of it (attributive meaning). They differ only in terms of the evidential mood that they convey. The <strong>assertive</strong>, <strong>egophoric</strong>, and <strong>revelatory</strong> moods are discussed below.</p>
", 
   "index": 0, 
   "parent_index": -1, 
   "title": "About The Essential Copulas: རེད་, ཡིན་, རེད་བཞག་"
  }
 ], 
 "meta": {
  "authors": [
   {
    "fullname": "Nicolas Tournadre", 
    "id": "6"
   }
  ], 
  "domain": "subjects", 
  "kid": "4775", 
  "dates": [], 
  "title": "About The Essential Copulas: རེད་, ཡིན་, རེད་བཞག་"
 }
}