{"meta":{"authors":[{"id":"7","fullname":"José I. Cabezón"}],"title":"","dates":{"created_at":"2013-09-15 04:08:53 UTC","updated_at":"2013-09-15 04:08:53 UTC"}},"nodes":[{"index":0,"parent_index":-1,"title":""},{"title":"Description","index":1,"parent_index":0,"body":"\n<p>Rituals designed to ensure long life.</p>\n"},{"title":"Related Terms","index":2,"parent_index":0,"body":"\n<p>tshe sgrub, tshe 'phel ba'i cho ga, tshe bsring ba'i cgo ga, srog sgrub</p>\n"},{"title":"Example Texts","index":3,"parent_index":0,"body":"\n<ul>\n<li>rnam rgyal ma'i tshe sgrub (<span class=\"summary_sub_descriptor_type\">W18789</span>)</li>\n<li>gu ru'i tshe chog (W28917)</li>\n<li>'od dpag med kyi tshe sgrub (W11711)</li>\n</ul>\n"},{"title":"Secondary Sources","index":4,"parent_index":0,"body":"\n<p><!--[if gte mso 9]><xml> Normal   0         false   false   false                             MicrosoftInternetExplorer4 </xml><![endif]--><!--[if gte mso 9]><xml> </xml><![endif]--><!--[if !mso]> <span class=\"mceItemObject\"   classid=\"clsid:38481807-CA0E-42D2-BF39-B33AF135CC4D\" id=ieooui> </span> <mce:style><!  st1\\:*{behavior:url(#i<![endif]--> <!--[endif]--><!--  --><!--[if gte mso 10]> <mce:style><!   /* Style Definitions */  table.MsoNormalTable \t{mso-style-name:\"Table Normal\"; \tmso-tstyle-rowband-size:0; \tmso-tstyle-colband-size:0; \tmso-style-noshow:yes; \tmso-style-parent:\"\"; \tmso-padding-alt:0in 5.4pt 0in 5.4pt; \tmso-para-margin:0in; \tmso-para-margin-bottom:.0001pt; \tmso-pagination:widow-orphan; \tfont-size:10.0pt; \tfont-family:\"Times New Roman\"; \tmso-ansi-language:#0400; \tmso-fareast-language:#0400; \tmso-bidi-language<![endif]--> <!--[endif]-->Bawden, C. R. \"Calling the Soul: A Mongolian Litany.\" <em>Bulletin of the School of Oriental and African Studies, University  of London</em> 25, no. 1-2 (1962): 81-103.</p>\n<p><!--[if gte mso 9]><xml> Normal   0         false   false   false                             MicrosoftInternetExplorer4 </xml><![endif]--><!--[if gte mso 9]><xml> </xml><![endif]--><!--[if !mso]> <span class=\"mceItemObject\"   classid=\"clsid:38481807-CA0E-42D2-BF39-B33AF135CC4D\" id=ieooui> </span> <mce:style><!  st1\\:*{behavior:url(#i<![endif]--> <!--[endif]--><!--  --><!--[if gte mso 10]> <mce:style><!   /* Style Definitions */  table.MsoNormalTable \t{mso-style-name:\"Table Normal\"; \tmso-tstyle-rowband-size:0; \tmso-tstyle-colband-size:0; \tmso-style-noshow:yes; \tmso-style-parent:\"\"; \tmso-padding-alt:0in 5.4pt 0in 5.4pt; \tmso-para-margin:0in; \tmso-para-margin-bottom:.0001pt; \tmso-pagination:widow-orphan; \tfont-size:10.0pt; \tfont-family:\"Times New Roman\"; \tmso-ansi-language:#0400; \tmso-fareast-language:#0400; \tmso-bidi-language<![endif]--> <!--[endif]-->Beyer, Stephan V. \"Acquisition: Initiation and Ritual Service.\" In <em>The Cult of Tārā: Magic and Ritual in Tibet,</em> 361-468. Berkeley: University of California Press, 1973.</p>\n<p><!--[if gte mso 9]><xml> Normal   0         false   false   false                             MicrosoftInternetExplorer4 </xml><![endif]--><!--[if gte mso 9]><xml> </xml><![endif]--><!--[if !mso]> <span class=\"mceItemObject\"   classid=\"clsid:38481807-CA0E-42D2-BF39-B33AF135CC4D\" id=ieooui> </span> <mce:style><!  st1\\:*{behavior:url(#i<![endif]--> <!--[endif]--><!--  --><!--[if gte mso 10]> <mce:style><!   /* Style Definitions */  table.MsoNormalTable \t{mso-style-name:\"Table Normal\"; \tmso-tstyle-rowband-size:0; \tmso-tstyle-colband-size:0; \tmso-style-noshow:yes; \tmso-style-parent:\"\"; \tmso-padding-alt:0in 5.4pt 0in 5.4pt; \tmso-para-margin:0in; \tmso-para-margin-bottom:.0001pt; \tmso-pagination:widow-orphan; \tfont-size:10.0pt; \tfont-family:\"Times New Roman\"; \tmso-ansi-language:#0400; \tmso-fareast-language:#0400; \tmso-bidi-language<![endif]--> <!--[endif]-->Lopez, Donald. \"A Prayer for the Long Life of the Dalai Lama.\" In <em>Buddhism in Practice</em>, edited by Donald Lopez, 170-175. Princeton: Princeton  University Press, 1995.</p>\n"},{"title":"Related Knowledge Map Categories","index":5,"parent_index":0,"body":"\n<ul>\n<li>\"Healing rituals\"</li>\n</ul>"}]}