{
 "nodes": [
  {
   "body": "<p>byis pa srung ba [TBRC T1027], bsrung ba dang za yig (footnote: Dung dkar tshig mdzod: “Putting into the mouth of a newborn infant a knot blessed with the mantra of the tutelary deity or a black piece of paper onto which a mantra has been written in gold for the sake of protecting [the infant] from harm by evil spirits and demons etc.”)</p>", 
   "index": 0, 
   "parent_index": -1, 
   "title": "About Children"
  }
 ], 
 "meta": {
  "date": "2013-09-15 04:09:34 UTC", 
  "domain": "subjects", 
  "kid": "2383", 
  "authors": [
   {
    "fullname": "José I. Cabezón", 
    "id": "7"
   }
  ], 
  "title": "About Children"
 }
}