{
 "nodes": [
  {
   "body": "<ul> <li><span class=\"tibetan\" title=\"Type ID here\">ཐམ་ཀ་</span> “Seal” (<em>thamγa</em> “mark,” “label”)</li> <li><span class=\"tibetan\" title=\"Type ID here\">དར་</span> “Silk” (<em>torγu</em>)</li> <li><span class=\"tibetan\" title=\"Type ID here\">པག་ཤི་</span><a href=\"#_ftn1\">[1]</a> “Master” (<em>bakshi</em>)</li> <li><span class=\"tibetan\" title=\"Type ID here\">ཨེམ་ཆི་</span> “Doctor” (<em>εmci</em>)</li> </ul><hr size=\"1\"><p><a href=\"#_ftnref1\">[1]</a> As seen, for example, in the name <span class=\"tibetan\" title=\"Type ID here\">ཀར་མ་པག་ཤི་</span>, which was the title of a master of the Karmapa school.</p>", 
   "index": 0, 
   "parent_index": -1, 
   "title": "About From Uighur"
  }
 ], 
 "meta": {
  "authors": [
   {
    "fullname": "Nicolas Tournadre", 
    "id": "6"
   }
  ], 
  "domain": "subjects", 
  "kid": "5321", 
  "dates": [], 
  "title": "About From Uighur"
 }
}