{
 "nodes": [
  {
   "body": "", 
   "index": 0, 
   "parent_index": -1, 
   "title": "Confession of Downfalls (of Bodhisattva Discipline)"
  }, 
  {
   "body": "<ul> <li><a href=\"http://tbrc.org/#!rid=W13069\">Ltung bshags kyi cho ga ‘grel pa dang bcas pa</a> </li> <li><a href=\"http://tbrc.org/#!rid=W2181\">Bde gshegs sum cu so lnga’i ltung bshags cho ga</a></li> <li>See also: Byang chub ltung bshags = Mahāyāna sūtra for confessions of downfalls; Mna’ bshags = Mahāyāna Buddhist formula for confession and atonement; Phung po gsum pa’i mdo = The Sūtra of the Three Heaps  </li> </ul>
", 
   "index": 1, 
   "parent_index": 0, 
   "title": "Example Texts"
  }
 ], 
 "meta": {
  "authors": [
   {
    "fullname": "José I. Cabezón", 
    "id": "7"
   }
  ], 
  "domain": "subjects", 
  "kid": "1849", 
  "dates": [], 
  "title": "Confession of Downfalls (of Bodhisattva Discipline)"
 }
}