{"feature":{"id":"22253","db_id":"22317","header":"Zhalu Gön","feature_types":[{"title":"Monastery","id":"104"}],"names":[{"id":"72574","language":"bod","view":"roman.popular","name":"Zhalu Gön","writing_system":"latin","phonetic_system":"thl.simple.transcrip"},{"id":"72575","language":"bod","view":"roman.scholar","name":"zhwa lu dgon","writing_system":"latin","orthographic_system":"thl.ext.wyl.translit"},{"id":"72574","language":"bod","view":"trad.chi","name":"Zhalu Gön","writing_system":"latin","phonetic_system":"thl.simple.transcrip"},{"id":"72574","language":"bod","view":"simp.chi","name":"Zhalu Gön","writing_system":"latin","phonetic_system":"thl.simple.transcrip"},{"id":"72573","language":"bod","view":"pri.tib.sec.roman","name":"ཞྭ་ལུ་དགོན།","writing_system":"tibt"},{"id":"72573","language":"bod","view":"pri.tib.sec.chi","name":"ཞྭ་ལུ་དགོན།","writing_system":"tibt"},{"id":"72574","language":"bod","view":"deva","name":"Zhalu Gön","writing_system":"latin","phonetic_system":"thl.simple.transcrip"}],"parents":[{"id":"925","db_id":"983","header":"Zhikatsé","feature_types":[{"id":"4452","title":"ADM3"},{"id":"546","title":"City"}],"has_shapes":1}],"children":[],"perspectives":[{"id":"1068913229","code":"pol.admin.hier","ancestors":[{"id":"13735","db_id":"13784","header":"Earth","feature_types":[{"id":"556","title":"Cultural Region"},{"id":"4512","title":"Planet"}],"has_shapes":0},{"id":"13740","db_id":"13789","header":"Asia","feature_types":[{"id":"556","title":"Cultural Region"},{"id":"2883","title":"Continent"}],"has_shapes":0},{"id":"13734","db_id":"13783","header":"Greater Himalayas \u0026 Tibetan Plateau","feature_types":[{"id":"556","title":"Cultural Region"}],"has_shapes":0},{"id":"1","db_id":"59","header":"China","feature_types":[{"id":"29","title":"Nation"}],"has_shapes":1},{"id":"2","db_id":"60","header":"Tibet Autonomous Region","feature_types":[{"id":"4450","title":"ADM1"},{"id":"543","title":"Autonomous region"}],"has_shapes":1},{"id":"924","db_id":"982","header":"Zhikatsé","feature_types":[{"id":"4451","title":"ADM2"},{"id":"513","title":"Prefecture"}],"has_shapes":1},{"id":"925","db_id":"983","header":"Zhikatsé","feature_types":[{"id":"4452","title":"ADM3"},{"id":"546","title":"City"}],"has_shapes":1},{"id":"22253","db_id":"22317","header":"Zhalu Gön","feature_types":[{"id":"104","title":"Monastery"}],"has_shapes":1}]},{"id":"1068913286","code":"cult.reg","ancestors":[{"id":"13735","db_id":"13784","header":"Earth","feature_types":[{"id":"556","title":"Cultural Region"},{"id":"4512","title":"Planet"}],"has_shapes":0},{"id":"13740","db_id":"13789","header":"Asia","feature_types":[{"id":"556","title":"Cultural Region"},{"id":"2883","title":"Continent"}],"has_shapes":0},{"id":"13734","db_id":"13783","header":"Greater Himalayas \u0026 Tibetan Plateau","feature_types":[{"id":"556","title":"Cultural Region"}],"has_shapes":0},{"id":"1","db_id":"59","header":"China","feature_types":[{"id":"29","title":"Nation"}],"has_shapes":1},{"id":"2","db_id":"60","header":"Tibet Autonomous Region","feature_types":[{"id":"4450","title":"ADM1"},{"id":"543","title":"Autonomous region"}],"has_shapes":1},{"id":"924","db_id":"982","header":"Zhikatsé","feature_types":[{"id":"4451","title":"ADM2"},{"id":"513","title":"Prefecture"}],"has_shapes":1},{"id":"925","db_id":"983","header":"Zhikatsé","feature_types":[{"id":"4452","title":"ADM3"},{"id":"546","title":"City"}],"has_shapes":1},{"id":"22253","db_id":"22317","header":"Zhalu Gön","feature_types":[{"id":"104","title":"Monastery"}],"has_shapes":1}]}],"nested_captions":[{"id":"16","language":"eng","content":"\u003cp\u003eZhalu is renowned for its 14th-century murals painted by Nepalese and the codification of Buddhist canonical literature, among other things.\u003c/p\u003e"}],"summaries":[{"id":11,"language":"eng","content":"\u003cp\u003eEstablished in the early eleventh century by \u003cspan class=\"person\" title=\"Type ID here\"\u003eChets\u0026uuml;n Sherap Jungn\u0026eacute;\u003c/span\u003e (\u003cem\u003e\u003cspan class=\"tibetan\" title=\"Type ID here\"\u003elce btsun shes rab \u0026rsquo;byung gnas\u003c/span\u003e\u003c/em\u003e), Zhalu has played an important role in the cultural life of \u003cspan class=\"place\" title=\"15354\"\u003eTsang\u003c/span\u003e (\u003cem\u003e\u003cspan class=\"tibetan\" title=\"15354\"\u003egtsang\u003c/span\u003e\u003c/em\u003e). Renowned for both its artistic and literary achievements, it was home to Nepalese artisans painting murals, teams of scribes creating fine volumes of Buddhist canonical literature, and a lively community of scholars, monks, and yogic practitioners from throughout Tibet.\u0026nbsp; \u003cspan class=\"person\" title=\"Type ID here\"\u003eBut\u0026ouml;n Rinchendrup\u003c/span\u003e (\u003cem\u003e\u003cspan class=\"tibetan\" title=\"Type ID here\"\u003ebu ston rin chen grub\u003c/span\u003e\u003c/em\u003e, 1290-1364),\u0026nbsp;\u003cspan class=\"person\" title=\"Type ID here\"\u003eZhalu Lotsawa Ch\u0026ouml;kyong Zangpo\u003c/span\u003e (\u003cem\u003e\u003cspan class=\"tibetan\" title=\"Type ID here\"\u003ezhwa lu lo tsA wa chos skyong bzang po\u003c/span\u003e\u003c/em\u003e, 1441-1528), and the nineteenth-century non-sectarian movement (\u003cem\u003e\u003cspan class=\"tibetan\" title=\"Type ID here\"\u003eris med\u003c/span\u003e\u003c/em\u003e) figure \u003cspan class=\"person\" title=\"Type ID here\"\u003eLosel Tenkyong\u003c/span\u003e (\u003cem\u003e\u003cspan class=\"tibetan\" title=\"Type ID here\"\u003eblo gsal bstan skyong\u003c/span\u003e\u003c/em\u003e) are leading figures in Zhalu\u0026rsquo;s history.\u003c/p\u003e"}],"nested_descriptions":[{"id":"1302","is_primary":"false","title":"An Introduction to Zhalu Monastery"}],"illustrations":[{"id":"11597","url":"http://mms.thlib.org/media_objects/11597.json","type":"mms"},{"id":"11589","url":"http://mms.thlib.org/media_objects/11589.json","type":"mms"}],"has_shapes":1,"has_altitudes":0,"closest_fid_with_shapes":22253,"interactive_map_url":"http://www.thlib.org/places/maps/interactive/#fid:22253","kmz_url":"http://places.kmaps.virginia.edu/features/gis_resources/22253.kmz","associated_resources":{"etymology_count":0,"related_feature_count":1,"description_count":1,"subject_count":5,"picture_count":88,"video_count":0,"document_count":0},"created_at":"2010-07-28T16:16:32.000+00:00","updated_at":"2012-03-09T01:34:03.000+00:00"}}