{"feature":{"id":"1862","db_id":"1697","header":"Consecration of pills","names":[{"id":"2629","language":"eng","view":"roman.popular","name":"Consecration of pills","writing_system":"latin"},{"id":"2629","language":"eng","view":"roman.scholar","name":"Consecration of pills","writing_system":"latin"},{"id":"2629","language":"eng","view":"simp.chi","name":"Consecration of pills","writing_system":"latin"},{"id":"2630","language":"bod","view":"pri.tib.sec.roman","name":"རིལ་སྒྲུབ།  རིལ་བུའི་སྒྲུབ་ཐབས་/ཚུལ།","writing_system":"tibt"},{"id":"2630","language":"bod","view":"pri.tib.sec.chi","name":"རིལ་སྒྲུབ།  རིལ་བུའི་སྒྲུབ་ཐབས་/ཚུལ།","writing_system":"tibt"},{"id":"2629","language":"eng","view":"deva","name":"Consecration of pills","writing_system":"latin"}],"parents":[{"id":"1856","db_id":"1691","header":"Consecration by object being consecrated"}],"children":[{"id":"1863","db_id":"1698","header":"Consecration of long-life pills"},{"id":"1864","db_id":"1699","header":"Consecration of maṇi pills"},{"id":"1865","db_id":"1700","header":"Consecration of “nectar” pills"},{"id":"1866","db_id":"1701","header":"Consecration of pills that “liberate through taste”"}],"ancestors":[{"id":"6403","db_id":"5837","header":"Tibet and Himalayas"},{"id":"5805","db_id":"5267","header":"Ritual"},{"id":"1808","db_id":"1643","header":"Tibetan ritual"},{"id":"1854","db_id":"1689","header":"Consecration"},{"id":"1856","db_id":"1691","header":"Consecration by object being consecrated"},{"id":"1862","db_id":"1697","header":"Consecration of pills"}],"nested_captions":[],"summaries":[],"nested_descriptions":[{"id":"415","is_primary":"true","title":"Consecration of Pills"}],"illustrations":[],"associated_resources":{"etymology_count":0,"related_feature_count":5,"description_count":1,"place_count":0,"picture_count":0,"video_count":0,"document_count":0},"created_at":"2013-09-15T04:07:49.000+00:00","updated_at":"2013-09-16T08:28:51.000+00:00"}}