{"feature":{"id":"732","db_id":"640","header":"Labrang","names":[{"id":"1140","language":"eng","view":"roman.popular","name":"Labrang","writing_system":"latin"},{"id":"1140","language":"eng","view":"roman.scholar","name":"Labrang","writing_system":"latin"},{"id":"1140","language":"eng","view":"simp.chi","name":"Labrang","writing_system":"latin"},{"id":"1141","language":"bod","view":"pri.tib.sec.roman","name":"བླ་བྲང་།","writing_system":"tibt"},{"id":"1141","language":"bod","view":"pri.tib.sec.chi","name":"བླ་བྲང་།","writing_system":"tibt"},{"id":"1140","language":"eng","view":"deva","name":"Labrang","writing_system":"latin"}],"parents":[{"id":"730","db_id":"638","header":"Amdo"}],"children":[],"ancestors":[{"id":"6403","db_id":"5837","header":"Tibet and Himalayas"},{"id":"305","db_id":"222","header":"Cultural Regions"},{"id":"699","db_id":"607","header":"Cultural Tibet"},{"id":"734","db_id":"642","header":"Northeast"},{"id":"730","db_id":"638","header":"Amdo"},{"id":"732","db_id":"640","header":"Labrang"}],"nested_captions":[],"summaries":[],"nested_descriptions":[{"id":"195","is_primary":"true","title":"An Overview of the Labrang Region"}],"illustrations":[],"associated_resources":{"etymology_count":0,"related_feature_count":1,"description_count":1,"place_count":0,"picture_count":0,"video_count":0,"document_count":0},"created_at":"2013-09-15T04:05:11.000+00:00","updated_at":"2013-09-16T08:19:11.000+00:00"}}