{"descriptions":[{"id":291,"title":"An Overview of the Drukpa Kagyü Tradition","content":"\u003cp\u003eThe numerous Drukpa Kagy\u0026uuml; ('brug pa bka' brgyud) sects draw their name from the Drukpa ('brug pa) monastery in southern Tibet founded by Tsangpa Gyar\u0026eacute; (gtsang pa rgya ras, 1161-1211), also known as Pelden Drukpa Rinpoche Yesh\u0026eacute; Dorj\u0026eacute; (dpal ldan 'brug pa rin po che ye shes rdo rje, 1161-1211). He himself was a disciple of Lingrepa Pema Dorj\u0026eacute; (gling ras pa pad ma rdo rje, 1128-88). G\u0026ouml;tsangpa (rgod tshang pa) is a major successor of Tsangpa Gyar\u0026eacute;.  Pema Karpo (pad ma dkar po, 1527-1592) is one of the more important Drukpa Kagy\u0026uuml; authors historically.  The Drukpa Kagy\u0026uuml; tradition eventually came to be dominant in Bhutan, where it is currently the official state religion equivalent to the status the Geluk sect enjoyed in Central Tibet prior to the Chinese takeover in 1959.\u003c/p\u003e","source_url":null,"is_primary":true,"created_at":"2013-09-15 04:05:49 UTC","updated_at":"2013-09-15 04:05:49 UTC","authors":[{"id":"2","fullname":"David Germano"}]}]}