{"descriptions":[{"id":1145,"title":"An Overview of the Horse","content":"\u003cp\u003eHorse is one of the livestock of Tibetan nomads. It plays a great role in their daily life: 1) it is the main transportation, 2) horse race is the only and the most important sport in Tibetan nomadic areas, 3) in agricultural areas, it is used for harvest to deliver crops from the field to home and well-known for its strength and speed, etc.\u003c/p\u003e","source_url":null,"is_primary":true,"created_at":"2013-09-15 04:13:59 UTC","updated_at":"2013-09-15 04:13:59 UTC","authors":[{"id":"17","fullname":"Pakpa Dondrup"}]}]}