{"feature":{"id":"4173","db_id":"3828","header":"Petroglyph","names":[{"id":"5699","language":"eng","view":"roman.popular","name":"Petroglyph","writing_system":"latin"},{"id":"5701","language":"bod","view":"roman.scholar","name":"brag rkos ri mo","writing_system":"latin","orthographic_system":"thl.ext.wyl.translit"},{"id":"5699","language":"eng","view":"simp.chi","name":"Petroglyph","writing_system":"latin"},{"id":"5700","language":"bod","view":"pri.tib.sec.roman","name":"བྲག་བརྐོས་རི་མོ།","writing_system":"tibt"},{"id":"5700","language":"bod","view":"pri.tib.sec.chi","name":"བྲག་བརྐོས་རི་མོ།","writing_system":"tibt"},{"id":"5699","language":"eng","view":"deva","name":"Petroglyph","writing_system":"latin"}],"parents":[{"id":"5398","db_id":"4874","header":"Rock Carving"}],"children":[],"ancestors":[{"id":"6403","db_id":"5837","header":"Tibet and Himalayas"},{"id":"20","db_id":"1","header":"Geographical Features"},{"id":"4100","db_id":"3755","header":"Archaic Monument and Rock Art"},{"id":"4144","db_id":"3799","header":"Rock Art and Epigraphy"},{"id":"5398","db_id":"4874","header":"Rock Carving"},{"id":"4173","db_id":"3828","header":"Petroglyph"}],"nested_captions":[],"summaries":[],"nested_descriptions":[{"id":"1099","is_primary":"true","title":"An Overview of the Petroglyph Feature"}],"illustrations":[],"associated_resources":{"etymology_count":0,"related_feature_count":1,"description_count":1,"place_count":0,"picture_count":0,"video_count":0,"document_count":0},"created_at":"2013-09-15T04:13:06.000+00:00","updated_at":"2013-09-16T08:45:09.000+00:00"}}