{"feature":{"id":"729","db_id":"637","header":"Lhasa","names":[{"id":"1134","language":"eng","view":"roman.popular","name":"Lhasa","writing_system":"latin"},{"id":"1134","language":"eng","view":"roman.scholar","name":"Lhasa","writing_system":"latin"},{"id":"1134","language":"eng","view":"simp.chi","name":"Lhasa","writing_system":"latin"},{"id":"1135","language":"bod","view":"pri.tib.sec.roman","name":"ལྷ་ས།","writing_system":"tibt"},{"id":"1135","language":"bod","view":"pri.tib.sec.chi","name":"ལྷ་ས།","writing_system":"tibt"},{"id":"1134","language":"eng","view":"deva","name":"Lhasa","writing_system":"latin"}],"parents":[{"id":"728","db_id":"636","header":"Ü"}],"children":[],"ancestors":[{"id":"6403","db_id":"5837","header":"Tibet and Himalayas"},{"id":"305","db_id":"222","header":"Cultural Regions"},{"id":"699","db_id":"607","header":"Cultural Tibet"},{"id":"722","db_id":"630","header":"Central"},{"id":"728","db_id":"636","header":"Ü"},{"id":"729","db_id":"637","header":"Lhasa"}],"nested_captions":[],"summaries":[],"nested_descriptions":[{"id":"193","is_primary":"true","title":"An Overview of the Lhasa Region"}],"illustrations":[],"associated_resources":{"etymology_count":0,"related_feature_count":1,"description_count":1,"place_count":0,"picture_count":0,"video_count":0,"document_count":0},"created_at":"2013-09-15T04:05:11.000+00:00","updated_at":"2013-09-16T08:19:10.000+00:00"}}