{"descriptions":[{"authors":[{"fullname":"Jann Ronis","id":"32"},{"fullname":"Jann Ronis","id":"32"}],"source_url":null,"content":"<p>Drakyap (<em><span class=\"tibetan\" title=\"Type ID here\">brag g.yab</span></em>) was a Gelukpa (<em><span class=\"tibetan\" title=\"Type ID here\">dge lugs pa</span></em>) monastic state that was formed in the aftermath of the destruction of the Beri (<em><span class=\"tibetan\" title=\"Type ID here\">be ri</span></em>) kingdom by the Gushri Khan in 1838. Peter Schwieger has done extensive work on Drakyap.</p>","created_at":"2011-07-13 16:54:30 UTC","updated_at":"2011-07-13 16:54:30 UTC","id":1287,"title":"An Overview of Drakyap","is_primary":false}]}