{"descriptions":[{"authors":[{"fullname":"Nicolas Tournadre","id":"6"}],"source_url":null,"content":"<p class=\"Paragraph\">These very common particles have the same meaning as imperatives formed with the verb alone, or formed with <span class=\"tibetan\" title=\"Type ID here\">རོགས་གནང་</span>, but refer to a lower register. In conversation they are pronounced respectively <em>da</em> and <em>sh</em>. They may be used with both honorific and non-honorific forms.</p> <ul> <li><span class=\"tibetan\" title=\"Type ID here\">གསུངས་དང་།</span> &ldquo;Say it.&rdquo;</li> <li><span class=\"tibetan\" title=\"Type ID here\">ཕེབས་དང་།</span> &ldquo;Go.&rdquo;</li> <li><span class=\"tibetan\" title=\"Type ID here\">ཕེབས་ཤིག</span> &ldquo;Go.&rdquo;</li> <li><span class=\"tibetan\" title=\"Type ID here\">བཞུགས་ཤིག</span> &ldquo;Sit down.&rdquo;</li> <li><span class=\"tibetan\" title=\"Type ID here\">བཞུགས་དང་།</span> &ldquo;Sit down.&rdquo;</li> <li><span class=\"tibetan\" title=\"Type ID here\">ཟོ་དང་།</span> &ldquo;Eat.&rdquo;</li> <li><span class=\"tibetan\" title=\"Type ID here\">ཉོན་དང་།</span> &ldquo;Listen.&rdquo;</li> <li><span class=\"tibetan\" title=\"Type ID here\">ལབ་དང་།</span> &ldquo;Speak.&rdquo;</li> <li><span class=\"tibetan\" title=\"Type ID here\">ལྟོས་ཤིག</span> &ldquo;Look.&rdquo;</li> </ul>","created_at":"2013-09-15 04:15:44 UTC","updated_at":"2013-09-15 04:15:44 UTC","id":1364,"title":null,"is_primary":true}]}