{"descriptions":[{"id":649,"title":"Exorcism of Curses and Black Magic","content":"\u003ch1\u003eRelated Terms\u003c/h1\u003e \u003cp\u003ebyad bzlog pa, byad grol/\u0026rsquo;grol, byad phur rbod gtong gi gnyen po\u003c/p\u003e \u003ch1\u003eExample Texts\u003c/h1\u003e \u003cul\u003e \u003cli\u003e\u003ca href=\"http://tbrc.org/#!rid=W17994\"\u003eSeng gdong gyi sgo nas byad \u0026lsquo;grol byed tshul\u003c/a\u003e\u0026nbsp;\u003c/li\u003e \u003cli\u003e\u003ca href=\"http://tbrc.org/#!rid=W14982\"\u003eBsam gtan bum chog byad grol\u003c/a\u003e\u0026nbsp;\u003c/li\u003e \u003cli\u003e\u003ca href=\"http://tbrc.org/#!rid=W22642\"\u003eThugs sgrub bar chad kun sel las rdo rje gtsug tor byad grol srung ba bcas khyer bder phyungs ba gdengs cho ga ral gri\u003c/a\u003e\u0026nbsp;\u003c/li\u003e \u003c/ul\u003e","source_url":null,"is_primary":true,"created_at":"2013-09-15 04:08:43 UTC","updated_at":"2014-02-27 19:19:53 UTC","authors":[{"id":"7","fullname":"José I. Cabezón"}]}]}